mdsetup/__init__.py
mdsetup/__main__.py
mdsetup/cli.py
mdsetup/commands/__init__.py
mdsetup/commands/cmd_create.py
mdsetup/commands/cmd_init.py
mdsetup/commands/cmd_solvate.py
mdsetup/libs/__init__.py
mdsetup/libs/template.py
mdsetup/libs/utils.py
mdsetup/py.typed
mdsetup/templates/amber/equil/md1.jinja2
mdsetup/templates/amber/equil/md11.jinja2
mdsetup/templates/amber/equil/md12.jinja2
mdsetup/templates/amber/equil/md13.jinja2
mdsetup/templates/amber/equil/md14.jinja2
mdsetup/templates/amber/equil/md15.jinja2
mdsetup/templates/amber/equil/md16.jinja2
mdsetup/templates/amber/equil/md2.jinja2
mdsetup/templates/amber/equil/min1.jinja2
mdsetup/templates/amber/equil/min11.jinja2
mdsetup/templates/amber/equil/min12.jinja2
mdsetup/templates/amber/equil/min13.jinja2
mdsetup/templates/amber/equil/min14.jinja2
mdsetup/templates/amber/equil/min15.jinja2
mdsetup/templates/amber/equil/min2.jinja2
mdsetup/templates/amber/equil/min3.jinja2
mdsetup/templates/amber/equil/min4.jinja2
mdsetup/templates/amber/leap/fixed.jinja2
mdsetup/templates/amber/leap/solvate.jinja2
mdsetup/templates/amber/leap/tleap.jinja2
mdsetup/templates/amber/prod/mdprod.jinja2
mdsetup/templates/amber/prod/mdst.jinja2
mdsetup/templates/amber/scripts/equilibrate.jinja2
mdsetup/templates/amber/scripts/production.jinja2
mdsetup-0.1.0.dist-info/LICENSE.md
mdsetup-0.1.0.dist-info/METADATA
mdsetup-0.1.0.dist-info/WHEEL
mdsetup-0.1.0.dist-info/entry_points.txt
mdsetup-0.1.0.dist-info/RECORD
