Metadata-Version: 2.1
Name: mdsetup
Version: 0.1.0
Summary: Molecular dynamics setup
Home-page: https://github.com/tclick/mdsetup
License: GPL v3
Author: Timothy H. Click
Author-email: timothy.click@briarcliff.edu
Requires-Python: >=3.9,<4.0
Classifier: Development Status :: 3 - Alpha
Classifier: Environment :: Console
Classifier: Intended Audience :: Science/Research
Classifier: License :: OSI Approved :: GNU General Public License v3 or later (GPLv3+)
Classifier: License :: Other/Proprietary License
Classifier: Operating System :: OS Independent
Classifier: Programming Language :: Python :: 3
Classifier: Programming Language :: Python :: 3.9
Classifier: Programming Language :: Python :: 3.10
Classifier: Programming Language :: Python :: 3.11
Classifier: Programming Language :: Python :: 3 :: Only
Classifier: Topic :: Scientific/Engineering :: Chemistry
Classifier: Topic :: Utilities
Requires-Dist: MDAnalysis (>=2.5,<3.0)
Requires-Dist: click-extra (>=4.2)
Requires-Dist: jinja2
Requires-Dist: loguru
Requires-Dist: netCDF4
Requires-Dist: typing-extensions
Project-URL: Changelog, https://github.com/tclick/mdsetup/releases
Project-URL: Documentation, https://mdsetup.readthedocs.io
Project-URL: Repository, https://github.com/tclick/mdsetup
